osiftool/__init__.py
osiftool/constants.py
osiftool/dockertool.py
osiftool/login.py
osiftool/main.py
osiftool/service.py
osiftool/util.py
osiftool-1.2.14.dist-info/METADATA
osiftool-1.2.14.dist-info/RECORD
osiftool-1.2.14.dist-info/WHEEL
osiftool-1.2.14.dist-info/dependency_links.txt
osiftool-1.2.14.dist-info/entry_points.txt
osiftool-1.2.14.dist-info/top_level.txt
