Metadata-Version: 2.1
Name: osiftool
Version: 1.2.14
Summary: Small python program select osiftool and change it using curses standard library 
Home-page: https://github.com/IoTKETI
Author: xoguskim
Author-email: thyun.kim@synctechno.com
License: MIT License
Keywords: osiftool,OSIF,KETI,cognitive,IoT
Platform: UNKNOWN
Classifier: Development Status :: 3 - Alpha
Classifier: Intended Audience :: Developers
Classifier: Programming Language :: Python
Classifier: Programming Language :: Python :: 2
Classifier: License :: OSI Approved :: MIT License
